{
  "employees": [
    {
      "status": true,
      "firstName": "kim ",
      "lastName": "kardashian",
      "phoneNumber": "(123) 456-7898",
      "email": "kardashian@kim.com",
      "department": "Sales",
      "salary": 2222,
      "entryDate": "2024-07-30T19:00:00.000Z",
      "leaveDate": "-",
      "id": "882522578"
    },
    {
      "id": "119014366",
      "status": false,
      "firstName": "Iman",
      "lastName": "Zahid",
      "phoneNumber": "(222) 222-2222",
      "email": "imanzahidzahid3@gmail.com",
      "department": "Sales",
      "salary": 222,
      "entryDate": "2024-07-29T19:00:00.000Z",
      "leaveDate": "2028-08-29T19:00:00.000Z"
    },
    {
      "id": "907022533",
      "status": true,
      "firstName": "Iman",
      "lastName": "Zahid",
      "phoneNumber": "(555) 555-5555",
      "email": "m.shehrozzahid76@gmail.com",
      "department": "Marketing",
      "salary": 2222,
      "entryDate": "2024-07-30T19:00:00.000Z",
      "leaveDate": "-"
    },
    {
      "status": false,
      "firstName": "Boran",
      "lastName": "Boraaaaaa",
      "phoneNumber": "(444) 444-4444",
      "email": "Bora@bora.com",
      "department": "IT",
      "salary": 55,
      "entryDate": "2024-07-30T19:00:00.000Z",
      "leaveDate": "2024-07-26T19:00:00.000Z",
      "id": "909060282"
    },
    {
      "id": "249143107",
      "status": true,
      "firstName": "sono",
      "lastName": "mono",
      "phoneNumber": "(399) 999-9999",
      "email": "s0no@mono.com",
      "department": "Marketing",
      "salary": 22222222,
      "entryDate": "2024-07-30T19:00:00.000Z",
      "leaveDate": "-"
    },
    {
      "id": "130390938",
      "status": true,
      "firstName": "rona",
      "lastName": "tona",
      "phoneNumber": "(444) 444-4444",
      "email": "rona@tona.com",
      "department": "Sales",
      "salary": 222,
      "entryDate": "2024-07-18T19:00:00.000Z",
      "leaveDate": "-"
    }
  ]
}